keycloak_auth/__init__.py
keycloak_auth/keycloak_auth.py
fastapi_keycloak_auth-1.0.2.dist-info/LICENSE
fastapi_keycloak_auth-1.0.2.dist-info/METADATA
fastapi_keycloak_auth-1.0.2.dist-info/WHEEL
fastapi_keycloak_auth-1.0.2.dist-info/top_level.txt
fastapi_keycloak_auth-1.0.2.dist-info/RECORD
